rekor_types/__init__.py
rekor_types/py.typed
rekor_types/_internal/__init__.py
rekor_types/_internal/alpine.py
rekor_types/_internal/cose.py
rekor_types/_internal/dsse.py
rekor_types/_internal/hashedrekord.py
rekor_types/_internal/helm.py
rekor_types/_internal/intoto.py
rekor_types/_internal/jar.py
rekor_types/_internal/rekord.py
rekor_types/_internal/rfc3161.py
rekor_types/_internal/rpm.py
rekor_types/_internal/tuf.py
sigstore_rekor_types-0.0.17.dist-info/LICENSE
sigstore_rekor_types-0.0.17.dist-info/METADATA
sigstore_rekor_types-0.0.17.dist-info/WHEEL
sigstore_rekor_types-0.0.17.dist-info/top_level.txt
sigstore_rekor_types-0.0.17.dist-info/RECORD
