Metadata-Version: 2.1
Name: sigstore-rekor-types
Version: 0.0.17
Summary: Python models for Rekor's API types
Author-email: Trail of Bits <opensource@trailofbits.com>
License: 
Project-URL: Homepage, https://pypi.org/project/sigstore-rekor-types
Project-URL: Documentation, https://trailofbits.github.io/sigstore-rekor-types/
Project-URL: Issues, https://github.com/trailofbits/sigstore-rekor-types/issues
Project-URL: Source, https://github.com/trailofbits/sigstore-rekor-types
Classifier: Programming Language :: Python :: 3
Classifier: License :: OSI Approved :: Apache Software License
Requires-Python: >=3.8
License-File: LICENSE
Requires-Dist: pydantic[email] <3,>=2
Requires-Dist: typing-extensions ; python_version < "3.9"
Provides-Extra: codegen
Requires-Dist: datamodel-code-generator >=0.25.2 ; extra == 'codegen'
Requires-Dist: sigstore-rekor-types[lint] ; extra == 'codegen'
Provides-Extra: dev
Requires-Dist: sigstore-rekor-types[codegen,doc,lint] ; extra == 'dev'
Requires-Dist: build ; extra == 'dev'
Provides-Extra: doc
Requires-Dist: pdoc <16.0,>=14.2 ; extra == 'doc'
Provides-Extra: lint
Requires-Dist: ruff <0.7.4 ; extra == 'lint'
Requires-Dist: mypy >=1.0 ; extra == 'lint'
